lazymodels/__init__.py
lazymodels/core.py
lazymodels/functional_only.py
lazymodels/wrappers.py
lazymodelsloader-0.1.0.dist-info/METADATA
lazymodelsloader-0.1.0.dist-info/WHEEL
lazymodelsloader-0.1.0.dist-info/top_level.txt
lazymodelsloader-0.1.0.dist-info/RECORD
